{
    "sfw": {
        "wave": "揮手",
        "wink": "眨眼",
        "tea": "喝茶",
        "bonk": "頭槌",
        "punch": "拳打",
        "poke": "戳戳",
        "bully": "欺負",
        "pat": "拍拍",
        "kiss": "親親",
        "kick": "踢腳",
        "blush": "臉紅",
        "feed": "餵食",
        "smug": "自滿",
        "hug": "擁抱",
        "cuddle": "蹭蹭",
        "cry": "哭哭",
        "cringe": "尷尬",
        "slap": "扇巴掌",
        "five": "擊掌",
        "glomp": "激動的抱抱",
        "happy": "開心",
        "hold": "握手",
        "nom": "輕輕咬",
        "smile": "微笑",
        "throw": "扔東西",
        "lick": "舔舔",
        "bite": "用力咬",
        "dance": "跳舞",
        "boop": "戳一戳",
        "sleep": "睡覺",
        "like": "喜歡",
        "kill": "殺",
        "tickle": "搔癢癢",
        "nosebleed": "流鼻血",
        "threaten": "威脅",
        "depression": "難過",
        "wolf_arts": "狼",
        "jahy_arts": "比基尼?",
        "neko_arts": "猫",
        "coffee_arts": "咖啡"
    },
    "nsfw": {
        "ass": "屁股",
        "anal": "肛交",
        "bdsm": "bdsm",
        "classic": "經典",
        "cum": "高潮",
        "creampie": "中出",
        "manga": "漫畫",
        "femdom": "調教",
        "hentai": "hentai",
        "incest": "亂倫",
        "masturbation": "自慰",
        "public": "公共場所",
        "ero": "性暗示",
        "orgy": "性派對",
        "elves": "妖精",
        "yuri": "百合",
        "pantsu": "胖次",
        "pussy": "鮑魚",
        "glasses": "眼鏡",
        "cuckold": "NTR",
        "blowjob": "口交",
        "boobjob": "乳交",
        "handjob": "手交",
        "footjob": "足交",
        "boobs": "胸部",
        "thighs": "大腿",
        "ahegao": "阿嘿顏",
        "uniform": "制服",
        "gangbang": "輪姦",
        "tentacles": "觸手",
        "gif": "gif",
        "nsfwNeko": "貓咪",
        "zettaiRyouiki": "絕對領域"
    },
    "wallpaper": {
        "wallpaper": "桌布",
        "mobileWallpaper": "手機桌布",
        "nsfwMobileWallpaper": "色圖手機桌布"
    }
}